Workbook

Sheet 1. Summary
A1: Cost Estimate
A2: Security Wearable Venture
A3: All build work in India. INR primary, SGD converted at the rate on the Assumptions sheet.
A5: Headline totals | B5: INR | C5: SGD | D5: Notes
A6: One-off build cost (likely, excl. retainer) | B6: ='4. One-off Build'!C13 -> 6379230 | C6: ='4. One-off Build'!D13 -> 85056.4 | D6: Cash needed before the first paying deployment
A7: Software build (man-days approach) | B7: ='3. Software Man-Days'!F26 -> 3886300 | C7: ='3. Software Man-Days'!G26 -> 51817.333 | D7: Subset of the one-off total — built by India team
A8: Per-device monthly cost @ 500 devices | B8: ='5. Per-Device Monthly'!D10 -> 18.666667 | C8: ='5. Per-Device Monthly'!D11 -> 18.666667 | D8: What one wrist on one officer costs us per month
A9: Monthly cash turns positive at | B9: ='6. Break-even'!B16 -> M4 | D9: First month monthly contribution goes positive
A10: One-off spend recovered at | B10: ='6. Break-even'!B17 -> M9 | D10: First month cumulative cash goes positive
A13: How to use this workbook
A14: Blue cells are inputs — edit these.
A15: Black cells are formulas — do not edit; they will recalculate.
A16: Green cells pull values from another sheet.
A17: Yellow fill marks the key assumptions to challenge first.
A19: Sheets
A20: 2. Assumptions | B20: FX rate, day rates by role, standing assumptions
A21: 3. Software Man-Days | B21: Work packages × role × days × INR day rate → software build cost
A22: 4. One-off Build | B22: All-in one-off spend: software + prototyping + patent + legal + cloud + retainer
A23: 5. Per-Device Monthly | B23: Recurring per-device cost at 100, 500, 1,000 devices
A24: 6. Break-even | B24: Fleet ramp, monthly contribution, cumulative cash
A25: 7. Sensitivity | B25: Four inputs that swing the answer most

Sheet 2. Assumptions
A1: Assumptions & FX
A2: All blue cells editable. Everything else follows.
A4: Foreign exchange
A5: SGD 1 = INR | B5: 75 | D5: Named FX_RATE. Every SGD figure divides an INR figure by this cell.
A7: Working days
A8: Standard working days per month | B8: 21 | D8: Used only for role-to-monthly-cost conversion where needed
A10: India engineering day rates (freelance / small studio, 2026)
A11: Role | B11: INR/day | C11: SGD/day | D11: Notes
A12: Tech Lead / Architect | B12: 15000 | C12: =B12/$B$5 -> 200 | D12: Senior IC, 10+ yrs, owns architecture & code review
A13: Senior Full-stack Engineer | B13: 10000 | C13: =B13/$B$5 -> 133.33333 | D13: Web + API, 6–8 yrs
A14: Mid Full-stack Engineer | B14: 6000 | C14: =B14/$B$5 -> 80 | D14: Web + API, 3–5 yrs
A15: Embedded / Firmware Engineer | B15: 12000 | C15: =B15/$B$5 -> 160 | D15: Wearable firmware, BLE, GPS, cellular modem
A16: AI / RAG Engineer | B16: 12000 | C16: =B16/$B$5 -> 160 | D16: LLM integration, retrieval, guardrails
A17: Mobile Engineer | B17: 8000 | C17: =B17/$B$5 -> 106.66667 | D17: Android/iOS companion, if needed
A18: DevOps / Cloud Engineer | B18: 10000 | C18: =B18/$B$5 -> 133.33333 | D18: Azure Singapore, Terraform, CI/CD, PDPA-aware
A19: UI / UX Designer | B19: 7000 | C19: =B19/$B$5 -> 93.333333 | D19: Officer wrist UI, control-room console, admin
A20: QA Engineer | B20: 5000 | C20: =B20/$B$5 -> 66.666667 | D20: Manual + automated test, field-trial support
A21: Security Consultant | B21: 18000 | C21: =B21/$B$5 -> 240 | D21: Threat model, pen-test coordination, DPIA input
A22: Project Manager | B22: 8000 | C22: =B22/$B$5 -> 106.66667 | D22: Coordination, stand-ups, delivery tracking
A24: Other standing assumptions
A25: Device hardware unit cost (INR) | B25: 40 | D25: Working assumption for SGD ~45 unit at the FX rate. Refine on Shenzhen/India quotes. | J25: =B25/75 -> 0.53333333
A26: Device life (months) | B26: 24 | D26: Amortisation period. Recycle-across-officers model assumed.
A27: SIM cost per device per month (INR) | B27: 6 | D27: Target ~SGD 5.50 volume price (SimTel, 400+ SIMs). SGD 8 fallback if volume slips. | J27: =B27/75 -> 0.08
A28: Cloud hosting per device per month (INR) | B28: 2 | D28: Azure Singapore, PDPA-compliant. Event storage, compute, monitoring. | J28: =B28/75 -> 0.026666667
A29: AI inference per device per month (INR) | B29: 1 | D29: ~200 queries/month/device @ constrained scope. Rises fast if scope creeps. | J29: =B29/75 -> 0.013333333
A30: Platform ops team monthly cost (INR) | B30: 4000 | D30: India-based support team, ~SGD 4,000/month. Two mid engineers + partial DevOps. Yellow: challenge first. | J30: =B30/75 -> 53.333333
A31: Subscription price per device per month (SGD) | B31: 75 | D31: Working assumption. Anchors break-even; refine after CIS pilot economics measured.
A32: Contingency % on one-off spend | B32: 0.1 | D32: Timeline risk buffer, not padding.

Sheet 3. Software Man-Days
A1: Software Build — Man-Days (India Team)
A2: Work packages × role × days × day rate. Day rates pulled from Assumptions.
A4: Work package | B4: Role | C4: Days | D4: INR/day | E4: SGD/day | F4: Line INR | G4: Line SGD | H4: Scope note
A5: Discovery & architecture | B5: Tech Lead / Architect | C5: 12 | D5: ='2. Assumptions'!$B$12 -> 15000 | E5: ='2. Assumptions'!$C$12 -> 200 | F5: =C5*D5 -> 180000 | G5: =F5/'2. Assumptions'!$B$5 -> 2400 | H5: System design, data model, integration points
A6: Discovery & architecture | B6: UI / UX Designer | C6: 6 | D6: ='2. Assumptions'!$B$19 -> 7000 | E6: ='2. Assumptions'!$C$19 -> 93.333333 | F6: =C6*D6 -> 42000 | G6: =F6/'2. Assumptions'!$B$5 -> 560 | H6: Journey maps for officer, control room, admin
A7: Officer wrist firmware | B7: Embedded / Firmware Engineer | C7: 55 | D7: ='2. Assumptions'!$B$15 -> 12000 | E7: ='2. Assumptions'!$C$15 -> 160 | F7: =C7*D7 -> 660000 | G7: =F7/'2. Assumptions'!$B$5 -> 8800 | H7: Watch firmware, BLE, GPS, cellular, battery mgmt
A8: Officer wrist firmware | B8: QA Engineer | C8: 15 | D8: ='2. Assumptions'!$B$20 -> 5000 | E8: ='2. Assumptions'!$C$20 -> 66.666667 | F8: =C8*D8 -> 75000 | G8: =F8/'2. Assumptions'!$B$5 -> 1000 | H8: Bench + field test
A9: Officer companion / on-device UX | B9: Mobile Engineer | C9: 15 | D9: ='2. Assumptions'!$B$17 -> 8000 | E9: ='2. Assumptions'!$C$17 -> 106.66667 | F9: =C9*D9 -> 120000 | G9: =F9/'2. Assumptions'!$B$5 -> 1600 | H9: Minimal companion app if device needs one
A10: Officer companion / on-device UX | B10: UI / UX Designer | C10: 6 | D10: ='2. Assumptions'!$B$19 -> 7000 | E10: ='2. Assumptions'!$C$19 -> 93.333333 | F10: =C10*D10 -> 42000 | G10: =F10/'2. Assumptions'!$B$5 -> 560 | H10: Wrist UI patterns, 5–6 emergency prompts
A11: Control room console (web) | B11: Senior Full-stack Engineer | C11: 35 | D11: ='2. Assumptions'!$B$13 -> 10000 | E11: ='2. Assumptions'!$C$13 -> 133.33333 | F11: =C11*D11 -> 350000 | G11: =F11/'2. Assumptions'!$B$5 -> 4666.6667 | H11: Live map, alerts, incident timeline
A12: Control room console (web) | B12: Mid Full-stack Engineer | C12: 25 | D12: ='2. Assumptions'!$B$14 -> 6000 | E12: ='2. Assumptions'!$C$14 -> 80 | F12: =C12*D12 -> 150000 | G12: =F12/'2. Assumptions'!$B$5 -> 2000 | H12: Table views, filters, drilldowns
A13: Control room console (web) | B13: UI / UX Designer | C13: 10 | D13: ='2. Assumptions'!$B$19 -> 7000 | E13: ='2. Assumptions'!$C$19 -> 93.333333 | F13: =C13*D13 -> 70000 | G13: =F13/'2. Assumptions'!$B$5 -> 933.33333 | H13: Console layout, alert states, RBAC surfaces
A14: Admin back-end | B14: Mid Full-stack Engineer | C14: 25 | D14: ='2. Assumptions'!$B$14 -> 6000 | E14: ='2. Assumptions'!$C$14 -> 80 | F14: =C14*D14 -> 150000 | G14: =F14/'2. Assumptions'!$B$5 -> 2000 | H14: Tenant setup, device provisioning, user mgmt
A15: Admin back-end | B15: UI / UX Designer | C15: 5 | D15: ='2. Assumptions'!$B$19 -> 7000 | E15: ='2. Assumptions'!$C$19 -> 93.333333 | F15: =C15*D15 -> 35000 | G15: =F15/'2. Assumptions'!$B$5 -> 466.66667 | H15: Admin screens
A16: AI / RAG assistant + guardrails | B16: AI / RAG Engineer | C16: 35 | D16: ='2. Assumptions'!$B$16 -> 12000 | E16: ='2. Assumptions'!$C$16 -> 160 | F16: =C16*D16 -> 420000 | G16: =F16/'2. Assumptions'!$B$5 -> 5600 | H16: Emergency prompts, SOP retrieval, domain guardrails
A17: AI / RAG assistant + guardrails | B17: Senior Full-stack Engineer | C17: 10 | D17: ='2. Assumptions'!$B$13 -> 10000 | E17: ='2. Assumptions'!$C$13 -> 133.33333 | F17: =C17*D17 -> 100000 | G17: =F17/'2. Assumptions'!$B$5 -> 1333.3333 | H17: API layer, prompt routing, logging
A18: Cloud, DevOps, CI/CD | B18: DevOps / Cloud Engineer | C18: 25 | D18: ='2. Assumptions'!$B$18 -> 10000 | E18: ='2. Assumptions'!$C$18 -> 133.33333 | F18: =C18*D18 -> 250000 | G18: =F18/'2. Assumptions'!$B$5 -> 3333.3333 | H18: Azure Singapore, Terraform, pipelines, PDPA-aware config
A19: Security review support | B19: Security Consultant | C19: 8 | D19: ='2. Assumptions'!$B$21 -> 18000 | E19: ='2. Assumptions'!$C$21 -> 240 | F19: =C19*D19 -> 144000 | G19: =F19/'2. Assumptions'!$B$5 -> 1920 | H19: Threat model, pen-test coordination, DPIA input
A20: QA end-to-end & regression | B20: QA Engineer | C20: 25 | D20: ='2. Assumptions'!$B$20 -> 5000 | E20: ='2. Assumptions'!$C$20 -> 66.666667 | F20: =C20*D20 -> 125000 | G20: =F20/'2. Assumptions'!$B$5 -> 1666.6667 | H20: Automation, regression suite, UAT support
A21: Project management | B21: Project Manager | C21: 40 | D21: ='2. Assumptions'!$B$22 -> 8000 | E21: ='2. Assumptions'!$C$22 -> 106.66667 | F21: =C21*D21 -> 320000 | G21: =F21/'2. Assumptions'!$B$5 -> 4266.6667 | H21: Coordination, stand-ups, sprint reviews, tracking
A22: Tech lead ongoing (code review, unblock) | B22: Tech Lead / Architect | C22: 20 | D22: ='2. Assumptions'!$B$12 -> 15000 | E22: ='2. Assumptions'!$C$12 -> 200 | F22: =C22*D22 -> 300000 | G22: =F22/'2. Assumptions'!$B$5 -> 4000 | H22: Cross-package code review, architecture calls
A24: Sub-total (base build) | C24: =SUM(C5:C22) -> 372 | F24: =SUM(F5:F22) -> 3533000 | G24: =SUM(G5:G22) -> 47106.667
A25: Rework buffer (10%) | C25: =ROUND(C24*0.1,0) -> 37 | F25: =ROUND(F24*0.1,0) -> 353300 | G25: =F25/'2. Assumptions'!$B$5 -> 4710.6667 | H25: Field-trial fixes, spec changes, integration surprises
A26: TOTAL software build | C26: =C24+C25 -> 409 | F26: =F24+F25 -> 3886300 | G26: =G24+G25 -> 51817.333 | H26: =SUM(G5,G6,G16,G17,G21,G22) -> 18160 | I26: =G26-H26 -> 33657.333
E27: New Cost | F27: =G27*75 -> 2524300 | G27: =I26 -> 33657.333
A29: Man-days by role (roll-up)
A30: Role | B30: Total days | D30: INR/day | F30: Total INR | G30: Total SGD
A31: Tech Lead / Architect | C31: =SUMIF(B5:B22,A31,C5:C22) -> 32 | D31: ='2. Assumptions'!$B$12 -> 15000 | F31: =C31*D31 -> 480000 | G31: =F31/'2. Assumptions'!$B$5 -> 6400
A32: Senior Full-stack Engineer | C32: =SUMIF(B5:B22,A32,C5:C22) -> 45 | D32: ='2. Assumptions'!$B$13 -> 10000 | F32: =C32*D32 -> 450000 | G32: =F32/'2. Assumptions'!$B$5 -> 6000
A33: Mid Full-stack Engineer | C33: =SUMIF(B5:B22,A33,C5:C22) -> 50 | D33: ='2. Assumptions'!$B$14 -> 6000 | F33: =C33*D33 -> 300000 | G33: =F33/'2. Assumptions'!$B$5 -> 4000
A34: Embedded / Firmware Engineer | C34: =SUMIF(B5:B22,A34,C5:C22) -> 55 | D34: ='2. Assumptions'!$B$15 -> 12000 | F34: =C34*D34 -> 660000 | G34: =F34/'2. Assumptions'!$B$5 -> 8800
A35: AI / RAG Engineer | C35: =SUMIF(B5:B22,A35,C5:C22) -> 35 | D35: ='2. Assumptions'!$B$16 -> 12000 | F35: =C35*D35 -> 420000 | G35: =F35/'2. Assumptions'!$B$5 -> 5600
A36: Mobile Engineer | C36: =SUMIF(B5:B22,A36,C5:C22) -> 15 | D36: ='2. Assumptions'!$B$17 -> 8000 | F36: =C36*D36 -> 120000 | G36: =F36/'2. Assumptions'!$B$5 -> 1600
A37: DevOps / Cloud Engineer | C37: =SUMIF(B5:B22,A37,C5:C22) -> 25 | D37: ='2. Assumptions'!$B$18 -> 10000 | F37: =C37*D37 -> 250000 | G37: =F37/'2. Assumptions'!$B$5 -> 3333.3333
A38: UI / UX Designer | C38: =SUMIF(B5:B22,A38,C5:C22) -> 27 | D38: ='2. Assumptions'!$B$19 -> 7000 | F38: =C38*D38 -> 189000 | G38: =F38/'2. Assumptions'!$B$5 -> 2520
A39: QA Engineer | C39: =SUMIF(B5:B22,A39,C5:C22) -> 40 | D39: ='2. Assumptions'!$B$20 -> 5000 | F39: =C39*D39 -> 200000 | G39: =F39/'2. Assumptions'!$B$5 -> 2666.6667
A40: Security Consultant | C40: =SUMIF(B5:B22,A40,C5:C22) -> 8 | D40: ='2. Assumptions'!$B$21 -> 18000 | F40: =C40*D40 -> 144000 | G40: =F40/'2. Assumptions'!$B$5 -> 1920
A41: Project Manager | C41: =SUMIF(B5:B22,A41,C5:C22) -> 40 | D41: ='2. Assumptions'!$B$22 -> 8000 | F41: =C41*D41 -> 320000 | G41: =F41/'2. Assumptions'!$B$5 -> 4266.6667
A42: Check: sum matches base sub-total | C42: =SUM(C31:C41) -> 372 | F42: =SUM(F31:F41) -> 3533000 | G42: =SUM(G31:G41) -> 47106.667

Sheet 4. One-off Build
A1: One-off Build Cost
A2: All figures INR primary; SGD converted at the Assumptions FX rate.
A4: Line item | B4: Low (INR) | C4: Likely (INR) | D4: Likely (SGD) | E4: Basis / note
A5: Software build (from Man-Days sheet) | B5: =ROUND(C5*0.85,0) -> 2145655 | C5: ='3. Software Man-Days'!F27 -> 2524300 | D5: ='3. Software Man-Days'!G27 -> 33657.333 | E5: Base + 10% rework buffer. See Sheet 3 for role split.
A6: Device prototyping (India — 2 rounds) | B6: 650000 | C6: 1200000 | D6: =C6/'2. Assumptions'!$B$5 -> 16000 | E6: Design fees + 2 prototype batches (~20 units) + bench/field testing. Shenzhen would be similar in SGD.
A7: Security & privacy reviews | B7: 650000 | C7: 1100000 | D7: =C7/'2. Assumptions'!$B$5 -> 14666.667 | E7: DPIA + counsel, external threat model, penetration test, supply-chain and OTA review.
A8: Patent filing India | B8: 195000 | C8: 325000 | D8: =C8/'2. Assumptions'!$B$5 -> 4333.3333 | E8: Agent + government + drafting. Mahesh prior filing ~INR 195k (SGD 3,000). Budget line: INR 325k (SGD 5,000).
A9: Cloud & infrastructure setup (one-off) | B9: 325000 | C9: 650000 | D9: =C9/'2. Assumptions'!$B$5 -> 8666.6667 | E9: Azure Singapore tenant, Terraform baseline, CI/CD, monitoring — one-off setup only. Run costs on Sheet 5.
A10: Technical Director retainer (3–4 months) | E10: agree monthly retainer, then fill in. Excluded from totals below.
A11: Sub-total (excl. retainer, excl. contingency) | B11: =SUM(B5:B9) -> 3965655 | C11: =SUM(C5:C9) -> 5799300 | D11: =SUM(D5:D9) -> 77324
A12: Contingency (see Assumptions %) | B12: =ROUND(B11*'2. Assumptions'!$B$32,0) -> 396566 | C12: =ROUND(C11*'2. Assumptions'!$B$32,0) -> 579930 | D12: =C12/'2. Assumptions'!$B$5 -> 7732.4 | E12: Percentage set on Assumptions sheet.
A13: TOTAL one-off (excl. retainer) | B13: =B11+B12 -> 4362221 | C13: =C11+C12 -> 6379230 | D13: =D11+D12 -> 85056.4
C14: =D14*75 -> 4954230 | D14: =D13-SUM(D7,D8) -> 66056.4
A15: Retainer add-on (fill when agreed)
A16: Monthly retainer (SGD)
A17: Months on retainer during build | D17: 3
A18: Retainer sub-total (SGD) | D18: =D16*D17 -> 0
A19: Retainer sub-total (INR) | C19: =D18*'2. Assumptions'!$B$5 -> 0
A21: ALL-IN ONE-OFF (incl. retainer) | C21: =C13+(D18*'2. Assumptions'!$B$5) -> 6379230 | D21: =D13+D18 -> 85056.4

Sheet 5. Per-Device Monthly
A1: Recurring Per-Device Monthly Cost
A2: What one wrist on one officer costs us per month, at three fleet sizes.
A4: Cost line | B4: Basis | C4: 100 devices | D4: 500 devices | E4: 1,000 devices | F4: Note
A5: Hardware amortisation | B5: Unit INR / device life (months) | C5: ='2. Assumptions'!$B$25/'2. Assumptions'!$B$26 -> 1.6666667 | D5: ='2. Assumptions'!$B$25/'2. Assumptions'!$B$26 -> 1.6666667 | E5: ='2. Assumptions'!$B$25/'2. Assumptions'!$B$26 -> 1.6666667 | F5: Same at every fleet — a device costs what it costs
A6: SIM & connectivity | B6: Target volume price | C6: ='2. Assumptions'!$B$27 -> 6 | D6: ='2. Assumptions'!$B$27 -> 6 | E6: ='2. Assumptions'!$B$27 -> 6 | F6: Dexter negotiating on 400+ SIMs
A7: Cloud hosting | B7: Storage, compute, monitoring | C7: ='2. Assumptions'!$B$28 -> 2 | D7: ='2. Assumptions'!$B$28 -> 2 | E7: ='2. Assumptions'!$B$28 -> 2 | F7: Azure Singapore, PDPA-compliant
A8: AI inference | B8: ~200 queries/month/device | C8: ='2. Assumptions'!$B$29 -> 1 | D8: ='2. Assumptions'!$B$29 -> 1 | E8: ='2. Assumptions'!$B$29 -> 1 | F8: Scope-constrained; rises fast if scope creeps
A9: Platform ops team (India) | B9: Monthly team cost / fleet size | C9: ='2. Assumptions'!$B$30/100 -> 40 | D9: ='2. Assumptions'!$B$30/500 -> 8 | E9: ='2. Assumptions'!$B$30/1000 -> 4 | F9: Falls sharply with scale. This line drives the whole per-device curve.
A10: TOTAL per device / month | C10: =SUM(C5:C9) -> 50.666667 | D10: =SUM(D5:D9) -> 18.666667 | E10: =SUM(E5:E9) -> 14.666667
A11: TOTAL SGD per device / month | C11: =C10 -> 50.666667 | D11: =D10 -> 18.666667 | E11: =E10 -> 14.666667
A13: Subscription pricing @ target margin
A14: Per-device cost (row 10) | C14: =C10 -> 50.666667 | D14: =D10 -> 18.666667 | E14: =E10 -> 14.666667 | F14: Summary sheet reads D14 (500-fleet).
A15: Per-device SGD cost | C15: =C11 -> 50.666667 | D15: =D11 -> 18.666667 | E15: =E11 -> 14.666667
A16: Price @ 50% margin (SGD) | C16: =C15/(1-0.5) -> 101.33333 | D16: =D15/(1-0.5) -> 37.333333 | E16: =E15/(1-0.5) -> 29.333333
A17: Price @ 70% margin (SGD) | C17: =C15/(1-0.7) -> 168.88889 | D17: =D15/(1-0.7) -> 62.222222 | E17: =E15/(1-0.7) -> 48.888889
A18: Working subscription price (Assumptions) | C18: ='2. Assumptions'!$B$31 -> 75 | D18: ='2. Assumptions'!$B$31 -> 75 | E18: ='2. Assumptions'!$B$31 -> 75 | F18: Anchor for break-even model.
A19: Contribution / device / month (SGD) | C19: =C18-C15 -> 24.333333 | D19: =D18-D15 -> 56.333333 | E19: =E18-E15 -> 60.333333

Sheet 6. Break-even
A1: Break-even (SGD)
A2: Monthly cash from M1 to M24. Assumes CIS 100 devices at M4, linear to 500 by M12, flat after.
A4: Line | B4: M1 | C4: M2 | D4: M3 | E4: M4 | F4: M5 | G4: M6 | H4: M7 | I4: M8 | J4: M9 | K4: M10 | L4: M11 | M4: M12 | N4: M13 | O4: M14 | P4: M15 | Q4: M16 | R4: M17 | S4: M18 | T4: M19 | U4: M20 | V4: M21 | W4: M22 | X4: M23 | Y4: M24
A5: Fleet size (devices) | B5: 0 | C5: 0 | D5: 0 | E5: 100 | F5: 150 | G5: 200 | H5: 250 | I5: 300 | J5: 350 | K5: 400 | L5: 450 | M5: 500 | N5: 500 | O5: 500 | P5: 500 | Q5: 500 | R5: 500 | S5: 500 | T5: 500 | U5: 500 | V5: 500 | W5: 500 | X5: 500 | Y5: 500
A6: Contribution per device (SGD) | B6: ='5. Per-Device Monthly'!$D$19 -> 56.333333 | C6: ='5. Per-Device Monthly'!$D$19 -> 56.333333 | D6: ='5. Per-Device Monthly'!$D$19 -> 56.333333 | E6: ='5. Per-Device Monthly'!$D$19 -> 56.333333 | F6: ='5. Per-Device Monthly'!$D$19 -> 56.333333 | G6: ='5. Per-Device Monthly'!$D$19 -> 56.333333 | H6: ='5. Per-Device Monthly'!$D$19 -> 56.333333 | I6: ='5. Per-Device Monthly'!$D$19 -> 56.333333 | ... Y6: ='5. Per-Device Monthly'!$D$19 -> 56.333333
A7: Monthly revenue (SGD) | B7: =B5*'5. Per-Device Monthly'!$D$18 -> 0 | C7: =C5*'5. Per-Device Monthly'!$D$18 -> 0 | D7: =D5*'5. Per-Device Monthly'!$D$18 -> 0 | E7: =E5*'5. Per-Device Monthly'!$D$18 -> 7500 | F7: =F5*'5. Per-Device Monthly'!$D$18 -> 11250 | G7: =G5*'5. Per-Device Monthly'!$D$18 -> 15000 | H7: =H5*'5. Per-Device Monthly'!$D$18 -> 18750 | I7: =I5*'5. Per-Device Monthly'!$D$18 -> 22500 | ... Y7: =Y5*'5. Per-Device Monthly'!$D$18 -> 37500
A8: Monthly cost (SGD) | B8: =B5*(SUM('5. Per-Device Monthly'!$D$5:$D$8)/'2. Assumptions'!$B$5) + ('2. Assumptions'!$B$30/'2. Assumptions'!$B$5) -> 53.333333 | C8: =C5*(SUM('5. Per-Device Monthly'!$D$5:$D$8)/'2. Assumptions'!$B$5) + ('2. Assumptions'!$B$30/'2. Assumptions'!$B$5) -> 53.333333 | D8: =D5*(SUM('5. Per-Device Monthly'!$D$5:$D$8)/'2. Assumptions'!$B$5) + ('2. Assumptions'!$B$30/'2. Assumptions'!$B$5) -> 53.333333 | E8: =E5*(SUM('5. Per-Device Monthly'!$D$5:$D$8)/'2. Assumptions'!$B$5) + ('2. Assumptions'!$B$30/'2. Assumptions'!$B$5) -> 67.555556 | F8: =F5*(SUM('5. Per-Device Monthly'!$D$5:$D$8)/'2. Assumptions'!$B$5) + ('2. Assumptions'!$B$30/'2. Assumptions'!$B$5) -> 74.666667 | G8: =G5*(SUM('5. Per-Device Monthly'!$D$5:$D$8)/'2. Assumptions'!$B$5) + ('2. Assumptions'!$B$30/'2. Assumptions'!$B$5) -> 81.777778 | H8: =H5*(SUM('5. Per-Device Monthly'!$D$5:$D$8)/'2. Assumptions'!$B$5) + ('2. Assumptions'!$B$30/'2. Assumptions'!$B$5) -> 88.888889 | I8: =I5*(SUM('5. Per-Device Monthly'!$D$5:$D$8)/'2. Assumptions'!$B$5) + ('2. Assumptions'!$B$30/'2. Assumptions'!$B$5) -> 96 | ... Y8: =Y5*(SUM('5. Per-Device Monthly'!$D$5:$D$8)/'2. Assumptions'!$B$5) + ('2. Assumptions'!$B$30/'2. Assumptions'!$B$5) -> 124.44444
A9: Monthly contribution (SGD) | B9: =B7-B8 -> -53.333333 | C9: =C7-C8 -> -53.333333 | D9: =D7-D8 -> -53.333333 | E9: =E7-E8 -> 7432.4444 | F9: =F7-F8 -> 11175.333 | G9: =G7-G8 -> 14918.222 | H9: =H7-H8 -> 18661.111 | I9: =I7-I8 -> 22404 | ... Y9: =Y7-Y8 -> 37375.556
A10: Cumulative cash (SGD) | B10: =-'4. One-off Build'!$D$13+B9 -> -85109.733 | C10: =B10+C9 -> -85163.067 | D10: =C10+D9 -> -85216.4 | E10: =D10+E9 -> -77783.956 | F10: =E10+F9 -> -66608.622 | G10: =F10+G9 -> -51690.4 | H10: =G10+H9 -> -33029.289 | I10: =H10+I9 -> -10625.289 | J10: =I10+J9 -> 15521.6 | ... Y10: =X10+Y9 -> 564926.27
A11: Cumulative cash (INR) | B11: =B10*'2. Assumptions'!$B$5 -> -6383230 | C11: =C10*'2. Assumptions'!$B$5 -> -6387230 | D11: =D10*'2. Assumptions'!$B$5 -> -6391230 | E11: =E10*'2. Assumptions'!$B$5 -> -5833796.7 | F11: =F10*'2. Assumptions'!$B$5 -> -4995646.7 | G11: =G10*'2. Assumptions'!$B$5 -> -3876780 | H11: =H10*'2. Assumptions'!$B$5 -> -2477196.7 | I11: =I10*'2. Assumptions'!$B$5 -> -796896.67 | ... Y11: =Y10*'2. Assumptions'!$B$5 -> 42369470
A15: Break-even indicators
A16: Monthly cash-positive from | B16: =INDEX($B$4:$Y$4, MATCH(1, $B$18:$Y$18, 0)) -> M4
A17: One-off spend recovered by | B17: =INDEX($B$4:$Y$4, MATCH(1, $B$19:$Y$19, 0)) -> M9
A18: Helper: monthly contrib flag | B18: =IF(B9>=0,1,0) -> 0 | C18: =IF(C9>=0,1,0) -> 0 | D18: =IF(D9>=0,1,0) -> 0 | E18: =IF(E9>=0,1,0) -> 1 | F18: =IF(F9>=0,1,0) -> 1 | G18: =IF(G9>=0,1,0) -> 1 | H18: =IF(H9>=0,1,0) -> 1 | I18: =IF(I9>=0,1,0) -> 1 | ... Y18: =IF(Y9>=0,1,0) -> 1
A19: Helper: cumulative flag | B19: =IF(B10>=0,1,0) -> 0 | C19: =IF(C10>=0,1,0) -> 0 | D19: =IF(D10>=0,1,0) -> 0 | E19: =IF(E10>=0,1,0) -> 0 | F19: =IF(F10>=0,1,0) -> 0 | G19: =IF(G10>=0,1,0) -> 0 | H19: =IF(H10>=0,1,0) -> 0 | I19: =IF(I10>=0,1,0) -> 0 | ... Y19: =IF(Y10>=0,1,0) -> 1
A21: Break-even is dynamic — change any assumption on Sheet 2 or fleet ramp in row 5 and rows 16 and 17 update.

Sheet 7. Sensitivity
A1: Sensitivity — the numbers that move the answer
A2: Change one input on Assumptions; watch break-even shift on Sheet 6.
A4: Swing | B4: Low case | C4: Base case | D4: High case | E4: What it does to the answer
A5: Unit hardware cost (INR) | B5: 1,900 (SGD 30) | C5: 2,900 (SGD 45) | D5: 6,500 (SGD 100) | E5: Per-device cost moves ~SGD 5 at 500 fleet. Break-even slips ~1 month at worst. Least sensitive line.
A6: SIM price (INR / month) | B6: 325 (SGD 5) | C6: 360 (SGD 5.5) | D6: 520 (SGD 8) | E6: ~SGD 2.50 per device swing. Break-even shifts ~1 month; more if pricing is squeezed.
A7: Fleet by M12 | B7: 300 devices | C7: 500 devices | D7: 750 devices | E7: THE biggest swing. Payback moves from ~M19 (base) to ~M25 (low) or ~M15 (high). Ramp speed dominates everything else.
A8: AI inference (INR/device/mo) | B8: 65 (SGD 1) | C8: 130 (SGD 2) | D8: 400 (SGD 6) | E8: Negligible at current scope. Material only if AI usage escapes guardrails and scope creeps.
A9: Platform team (INR/month) | B9: 195,000 (SGD 3k) | C9: 260,000 (SGD 4k) | D9: 520,000 (SGD 8k) | E9: Second biggest swing. Every SGD 1k on the team pushes ~2 months into break-even. Largest recurring line.
A12: The uncomfortable finding
A13: The model is most sensitive to ramp speed and the platform team — both within our control — and least sensitive to hardware cost, where procurement attention naturally goes. Spend management attention where the numbers say.
